flowmind/__init__.py
flowmind/agent.py
flowmind/core/__init__.py
flowmind/core/context.py
flowmind/core/pipeline.py
flowmind/core/scheduler.py
flowmind/core/task.py
flowmind/plugins/__init__.py
flowmind/plugins/loader.py
flowmind/plugins/registry.py
flowmind/storage/__init__.py
flowmind/storage/cache.py
flowmind/storage/local.py
flowmind/tasks/__init__.py
flowmind/tasks/data_task.py
flowmind/tasks/email_task.py
flowmind/tasks/file_task.py
flowmind/tasks/ml_task.py
flowmind/tasks/pdf_task.py
flowmind/tasks/shell_task.py
flowmind/tasks/web_task.py
flowmind/utils/__init__.py
flowmind/utils/helpers.py
flowmind/utils/logger.py
flowmind/utils/validator.py
flowmind-0.1.0.dist-info/licenses/LICENSE
flowmind-0.1.0.dist-info/METADATA
flowmind-0.1.0.dist-info/WHEEL
flowmind-0.1.0.dist-info/top_level.txt
flowmind-0.1.0.dist-info/RECORD
