Metadata-Version: 2.4
Name: flowmind
Version: 0.1.0
Summary: A lightweight multi-agent automation platform for enterprise tasks
Home-page: https://github.com/idrissbado/flowmind
Author: Idriss Bado
Author-email: Idriss Bado <idrissbado@gmail.com>
License: MIT
Project-URL: Homepage, https://github.com/idrissbado/flowmind
Project-URL: Repository, https://github.com/idrissbado/flowmind
Project-URL: Documentation, https://github.com/idrissbado/flowmind#readme
Project-URL: Bug Tracker, https://github.com/idrissbado/flowmind/issues
Keywords: automation,workflow,agent,tasks,enterprise,no-code
Classifier: Development Status :: 4 - Beta
Classifier: Intended Audience :: Developers
Classifier: License :: OSI Approved :: MIT License
Classifier: Programming Language :: Python :: 3
Classifier: Programming Language :: Python :: 3.8
Classifier: Programming Language :: Python :: 3.9
Classifier: Programming Language :: Python :: 3.10
Classifier: Programming Language :: Python :: 3.11
Classifier: Programming Language :: Python :: 3.12
Classifier: Topic :: Software Development :: Libraries :: Python Modules
Classifier: Topic :: Office/Business :: Office Suites
Requires-Python: >=3.8
License-File: LICENSE
Provides-Extra: full
Requires-Dist: PyPDF2>=3.0.0; extra == "full"
Requires-Dist: scikit-learn>=1.0.0; extra == "full"
Requires-Dist: beautifulsoup4>=4.12.0; extra == "full"
Requires-Dist: requests>=2.31.0; extra == "full"
Dynamic: author
Dynamic: home-page
Dynamic: license-file
Dynamic: requires-python
